## 2.1  class文件的结构

Class文件是一组以8位字节为基础单位的二进制流，内容是以《Java虚拟机规范》规定的一种固定的格式存储数据。
存储数据用到了两个数据类型：`无符号数`和`表`。

+ 无符号数：无符号数是基本数据类型，以u1、u2、u4、u8来分别代表1个字节、2个字节、4个字节和8个字节的无符号数，无符号数可以用来描述数字、索引引用、数量表或者按照UTF-8编码构成字符串值。
+ 表：由多个无符号数或者其他表作为数据项构成的复合数据类型，以“_info”结尾，用于描述有层次关系的复合结构的数据。

看懂字节码文件的还需要了解下面的两个基本概念。

+ 全限定名：一个类的全限定名是将类全名的.全部替换为/，如java.lang.String替换为java/lang/String，全限定名称之间用“;”分割。
+ 描述符：描述符用来描述字段的数据类型、方法的参数类表和返回值，每种符号对应不同数据类型，如表2-1。

表2-1 Java类型与描述符号

| 描述符 | 类型                  |
|-----|---------------------|
| B   | 	byte               |
| C   | 	char               |
| D   | 	double             |
| F   | 	float              |
| I   | 	int                |
| J   | 	long               |
| S   | 	short              |
| Z   | 	boolean            |
| V   | 	void               |
| L   | 	Ljava/lang/Object; |

一般情况下类型描述符号是基本类型的首字母大写，其中有几个比较特殊：J、L和Z。
这三个需要特别记忆一下：J表示long；L表示对象；Z表示boolean。

表2-2为《Java虚拟机规范》规定的Class文件的固定格式，所有Class文件均按照以下格式存储内容。(
注意：每个class文件内容都是按照以下列表按列表中从上到下顺序组成，如果某些类型不涉及可以为空)

表2-2 class文件的格式

| 类型             | 名称                  | 数量                    | 占用字节数 | 含义          |
|----------------|---------------------|-----------------------|-------|-------------|
| u4             | magic               | 1                     | 4     | 魔数          
| u2             | minor_version       | 1                     | 2     | 次版本         |
| u2             | major_version       | 1                     | 2     | 主版本         |
| u2             | constant_pool_count | 1                     | 2     | 常量池容量计数     |
| cp_info        | constant_pool       | constant_pool_count-1 | 表结构   | 常量池表        |
| u2             | access_flags        | 1                     | 2     | 类的访问标识      |
| u2             | this_class          | 1                     | 2     | 类索引         |
| u2             | super_class         | 1                     | 2     | 父类索引        |
| u2             | interfaces_count    | 1                     | 2     | 实现的接口计数     |
| u2             | interfaces          | interfaces_count      | 表结构   | 实现的接口结构表    |
| u2             | fields_count        | 1                     | 2     | 类字段计数值      |
| field_info     | fields              | fields_count          | 表结构   | 字段结构表       |
| u2             | methods_count       | 1                     | 2     | 类方法计数值      |
| method_info    | methods             | methods_count         | 表结构   | 类方法结构表      |
| u2             | attributes_count    | 1                     | 2     | class属性数组长度 |
| attribute_info | attributes          | attributes_count      | 表结构   | 属性结构表       |

JVM规范要求每一个字节码文件都要由这十部分按照固定的顺序组成，整体结构如图2-1所示：



> 图2-1 class文件的整体结构




本节将用下面的代码来说明类的结构，代码清单2-1中的Foo类中仅有一个main方法。
> 代码 2-1

```java
public class Foo {
    public static void main(String[] args) {
        System.out.println("hello word!");
    }
}
```

> 图2-2 Foo.class文件数据

### 2.1.1 class文件头

先看前面的8个字节： CA FE BA BE 00 00 00 34
前4个字节是class文件的魔数，固定为CAFEBABE，它的作用是确定这个class文件能否被JVM虚拟机接受，
在类加载器加载class文件到内存上的时候，前八个字节不为"CAFEBABE"的文件会被拒绝。
后4个字节分为次版本和主版本号，其中主版本为0034，也就是52，对应于JDK8，而次版本一般为0。
如果类文件的版本号高于JVM自身的版本号，加载该类会抛出java.lang.UnsupportedClassVersionError错误。
Java的版本号是从45开始的，JDK1.1之后的每个JDK大版本发布，一般主版本号向上加1，高版本的JDK能向下兼容以前版本的class文件，
但是不能运行版本号高于当前JVM版本的文件，即使文件格式并未发生任何变化，虚拟机也必须拒绝执行超过其版本号的class文件。
已经发布版本的大版本号如下表2-3所示。

> 表2-3 Java版本与major version的关系

| JDK版本	  | Major | 
|---------|-------|
| Java1.1 | 	45   |
| Java1.2 | 	46   |
| Java1.3 | 	47   |
| Java1.4 | 	48   |
| Java5	  | 49    |
| Java6	  | 50    |
| Java7	  | 51    |
| Java8	  | 52    |
| Java9	  | 53    |
| Java10  | 	54   |
| Java11  | 	55   |
| Java17  | 	61   |
| Java18  | 	62   | 

### 2.1.2  常量池

紧接着主版本号之后的字节为常量池入口。常量池中存储两类常量：字面量与符号引用。字面量为代码中声明为final的常量值，符号引用如类和接口的全局限定名、字段的名称和描述符、方法的名称和描述符。
常量池整体上分为两部分：常量池计数器以及常量池数据区，如图2-3所示。
